stmapy/__init__.py
stmapy/_version.py
stmapy/citswidget.py
stmapy/config.json
stmapy/main.py
stmapy/matplotlibwidget.py
stmapy/plotting.py
stmapy/processing.py
stmapy/reads.py
stmapy/shape.py
stmapy/stmapyStyle.mplstyle
stmapy/ui_citswidget.ui
stmapy-0.5.2.dist-info/LICENSE
stmapy-0.5.2.dist-info/METADATA
stmapy-0.5.2.dist-info/WHEEL
stmapy-0.5.2.dist-info/entry_points.txt
stmapy-0.5.2.dist-info/top_level.txt
stmapy-0.5.2.dist-info/RECORD
