Metadata-Version: 2.1
Name: stmapy
Version: 0.5.2
Summary: Scanning tunneling microscopy analysis in Python
Home-page: https://github.com/cea-lateqs/STMapy
Author-email: loic.huder@gmail.com, florie.mesple@gmail.com
Classifier: Programming Language :: Python :: 3
Classifier: License :: OSI Approved :: MIT License
Classifier: Operating System :: OS Independent
Classifier: Intended Audience :: Science/Research
Classifier: Topic :: Scientific/Engineering :: Physics
Classifier: Topic :: Scientific/Engineering :: Visualization
Classifier: Environment :: X11 Applications :: Qt
Requires-Python: >=3.6
License-File: LICENSE
Requires-Dist: numpy
Requires-Dist: scipy >=0.17
Requires-Dist: matplotlib >=2.0
Requires-Dist: PyQt5
Requires-Dist: access2thematrix
